MANIFEST.in
setup.py
pytest_aoreporter/__init__.py
pytest_aoreporter/plugin.py
pytest_aoreporter.egg-info/PKG-INFO
pytest_aoreporter.egg-info/SOURCES.txt
pytest_aoreporter.egg-info/dependency_links.txt
pytest_aoreporter.egg-info/entry_points.txt
pytest_aoreporter.egg-info/requires.txt
pytest_aoreporter.egg-info/top_level.txt
pytest_aoreporter/html/heading.html
pytest_aoreporter/html/report.html
pytest_aoreporter/html/template.html