Metadata-Version: 2.1
Name: pytest-aoreporter
Version: 0.1.1
Summary: pytest report
Home-page: https://github.com/ae86sen/pytest-aoreporter
Author: ancientone
Author-email: listeningsss@163.com
Classifier: Programming Language :: Python :: 3
Classifier: License :: OSI Approved :: MIT License
Classifier: Operating System :: OS Independent
